<MSG_LOG><MSG STRUCTURE="diag_log_msg1" NAME="dmac_tx_addba_req_proc:addba_req_proc_cb return [%d] @dmac_blockack_rom.c(149),WARNING" ID="0x801c04ab" />
			<MSG STRUCTURE="diag_log_msg1" NAME="vap_id[%d] {dmac_config_tx_addba_req::release mem} @dmac_blockack_rom.c(165),ERROR" ID="0x801c052a" />
			<MSG STRUCTURE="diag_log_msg1" NAME="vap_id[%d] {dmac_config_tx_addba_req::ba_tx_hdl null.} @dmac_blockack_rom.c(171),ERROR" ID="0x801c055a" />
			<MSG STRUCTURE="diag_log_msg1" NAME="dmac_rx_addba_rsp_proc:addba_resp_proc_cb return [%d] @dmac_blockack_rom.c(302),WARNING" ID="0x801c0973" />
			<MSG STRUCTURE="diag_log_msg2" NAME="vap_id[%d] {dmac_config_rx_addba_rsp::ba_tx_hdl null. tidno:%d} @dmac_blockack_rom.c(321),WARNING" ID="0x801c0a0b" />
			<MSG STRUCTURE="diag_log_msg1" NAME="{dmac_ba_get_min_len_ht::invalid ht_mcs[%d].} @dmac_blockack_rom.c(378),ERROR" ID="0x801c0bd2" />
			<MSG STRUCTURE="diag_log_msg2" NAME="{dmac_ba_get_min_len_he::array over flow, he_mcs=%d nss=%d.} @dmac_blockack_rom.c(423),ERROR" ID="0x801c0d3a" />
			<MSG STRUCTURE="diag_log_msg1" NAME="vap_id[%d] {dmac_ba_send_bar::dmac_vap null.} @dmac_blockack_rom.c(549),ERROR" ID="0x801c112a" />
			<MSG STRUCTURE="diag_log_msg1" NAME="vap_id[%d] {dmac_ba_send_bar::alloc netbuff failed.} @dmac_blockack_rom.c(558),WARNING" ID="0x801c1173" />
			<MSG STRUCTURE="diag_log_msg1" NAME="vap_id[%d] {dmac_ba_send_bar::bar_len=0.} @dmac_blockack_rom.c(564),ERROR" ID="0x801c11a2" />
			<MSG STRUCTURE="diag_log_msg2" NAME="vap_id[%d] {dmac_ba_send_bar::dmac_tx_mgmt_enqueue failed[%d].} @dmac_blockack_rom.c(574),WARNING" ID="0x801c11f3" />
			<MSG STRUCTURE="diag_log_msg0" NAME="{dmac_roam_reset_ba::dmac_vap is NULL.} @dmac_blockack_rom.c(597),WARNING" ID="0x801c12ab" />
			<MSG STRUCTURE="diag_log_msg1" NAME="{dmac_roam_reset_ba:: TID[%d]:reset rx ba.} @dmac_blockack_rom.c(611),WARNING" ID="0x801c131b" />
			<MSG STRUCTURE="diag_log_msg1" NAME="{dmac_roam_reset_ba:: TID[%d]:reset tx ba.} @dmac_blockack_rom.c(616),WARNING" ID="0x801c1343" />
			<MSG STRUCTURE="diag_log_msg4" NAME="vap_id[%d] {dmac_config_start_ampdu::ampdu ht size=%d, vth size %d, tx_mode=%d.} @dmac_blockack_rom.c(645),WARNING" ID="0x801c142b" />
			<MSG STRUCTURE="diag_log_msg4" NAME="{req seq num=%d,rsp seq num=%d,req policy=%d,rsp policy=%d} @dmac_blockack_rom.c(690),WARNING" ID="0x801c1593" />
			<MSG STRUCTURE="diag_log_msg0" NAME="{dmac_ba_encap_blockack_req:: ba_tx_hdl is null} @dmac_blockack_rom.c(743),ERROR" ID="0x801c173a" />
			<MSG STRUCTURE="diag_log_msg0" NAME="{dmac_ba_addba_req_set_ssn:: param is null} @dmac_blockack_rom.c(818),ERROR" ID="0x801c1992" />
			<MSG STRUCTURE="diag_log_msg1" NAME="{dmac_ba_addba_req_set_ssn:: user[%d] is null} @dmac_blockack_rom.c(825),ERROR" ID="0x801c19ca" />
			<MSG STRUCTURE="diag_log_msg1" NAME="vap_id[%d] {dmac_tx_delete_ba::failed} @dmac_blockack_rom.c(885),ERROR" ID="0x801c1baa" />
			<MSG STRUCTURE="diag_log_msg0" NAME="dmac_config_set_ampdu_tx_hw_on input param is null! @dmac_blockack_rom.c(897),ERROR" ID="0x801c1c0a" />
			</MSG_LOG>